[
  {
    "id": "REM-001",
    "source": "Email",
    "receivedAt": "2024-12-01T07:55:00Z",
    "payerName": "Amazon Web Services",
    "customerId": "C-AWS",
    "paymentId": "PAY-001",
    "documentType": "PDF",
    "fileName": "AWS_Remittance_Dec2024.pdf",
    "extractedAmount": 45230.50,
    "invoiceReferences": ["INV-001", "INV-002"],
    "status": "Processed",
    "confidence": 95,
    "rawText": "Payment for invoices INV-001 ($30,150.50) and INV-002 ($15,080.00). Total: $45,230.50"
  },
  {
    "id": "REM-002",
    "source": "EDI",
    "receivedAt": "2024-12-01T09:10:00Z",
    "payerName": "Microsoft Corporation",
    "customerId": "C-MSFT",
    "paymentId": "PAY-002",
    "documentType": "EDI_820",
    "fileName": null,
    "extractedAmount": 128750.00,
    "invoiceReferences": ["INV-003", "INV-004", "INV-005"],
    "status": "Processed",
    "confidence": 98,
    "rawText": null
  },
  {
    "id": "REM-003",
    "source": "Lockbox",
    "receivedAt": "2024-12-02T10:25:00Z",
    "payerName": "Acme Corp",
    "customerId": "C-ACME",
    "paymentId": "PAY-003",
    "documentType": "CheckStub",
    "fileName": "Lockbox_Batch_120224_003.tif",
    "extractedAmount": 8920.75,
    "invoiceReferences": ["INV-006"],
    "status": "Processed",
    "confidence": 88,
    "rawText": "Check #4521 for Invoice INV-006"
  },
  {
    "id": "REM-004",
    "source": "Portal",
    "receivedAt": "2024-12-02T10:55:00Z",
    "payerName": "Salesforce Inc",
    "customerId": "C-SFDC",
    "paymentId": "PAY-004",
    "documentType": "CSV",
    "fileName": "SFDC_Payment_120224.csv",
    "extractedAmount": 250000.00,
    "invoiceReferences": ["INV-007", "INV-008", "INV-009", "INV-010"],
    "status": "Processed",
    "confidence": 99,
    "rawText": null
  },
  {
    "id": "REM-005",
    "source": "Email",
    "receivedAt": "2024-12-03T07:40:00Z",
    "payerName": "Oracle Corporation",
    "customerId": "C-ORCL",
    "paymentId": "PAY-005",
    "documentType": "PDF",
    "fileName": "Oracle_Remit_120324.pdf",
    "extractedAmount": 15340.25,
    "invoiceReferences": ["INV-011", "INV-012"],
    "status": "Processed",
    "confidence": 92,
    "rawText": "Payment advice: INV-011 $10,240.25, INV-012 $5,100.00"
  },
  {
    "id": "REM-006",
    "source": "Email",
    "receivedAt": "2024-12-05T12:50:00Z",
    "payerName": "Zoom Video",
    "customerId": "C-ZM",
    "paymentId": "PAY-013",
    "documentType": "PDF",
    "fileName": "Zoom_Remit_120524.pdf",
    "extractedAmount": 12750.00,
    "invoiceReferences": ["INV-020"],
    "status": "NeedsReview",
    "confidence": 62,
    "rawText": "Payment for INV-020. Note: Deducting $500 for early payment discount."
  },
  {
    "id": "REM-007",
    "source": "EDI",
    "receivedAt": "2024-12-06T07:55:00Z",
    "payerName": "Cisco Systems",
    "customerId": "C-CSCO",
    "paymentId": "PAY-014",
    "documentType": "EDI_820",
    "fileName": null,
    "extractedAmount": 87300.00,
    "invoiceReferences": ["INV-021"],
    "status": "NeedsReview",
    "confidence": 45,
    "rawText": null
  },
  {
    "id": "REM-008",
    "source": "Email",
    "receivedAt": "2024-12-06T09:40:00Z",
    "payerName": "Shopify Inc",
    "customerId": null,
    "paymentId": "PAY-015",
    "documentType": "PDF",
    "fileName": "Shopify_Payment_Dec.pdf",
    "extractedAmount": 5600.00,
    "invoiceReferences": ["INV-UNKNOWN-001"],
    "status": "NeedsReview",
    "confidence": 30,
    "rawText": "Wire transfer for outstanding balance. Ref: PO-44521"
  },
  {
    "id": "REM-009",
    "source": "Lockbox",
    "receivedAt": "2024-12-07T09:55:00Z",
    "payerName": "Twilio Inc",
    "customerId": "C-TWLO",
    "paymentId": "PAY-017",
    "documentType": "CheckStub",
    "fileName": "Lockbox_Batch_120724_017.tif",
    "extractedAmount": 2300.00,
    "invoiceReferences": ["INV-023"],
    "status": "NeedsReview",
    "confidence": 70,
    "rawText": "Check #8832 for INV-023. Short pay - damaged goods claim ref DC-2024-089"
  },
  {
    "id": "REM-010",
    "source": "Email",
    "receivedAt": "2024-12-08T07:55:00Z",
    "payerName": "HubSpot",
    "customerId": "C-HUBS",
    "paymentId": "PAY-018",
    "documentType": "PDF",
    "fileName": "HubSpot_Remittance_Dec.pdf",
    "extractedAmount": 33450.75,
    "invoiceReferences": ["INV-024", "INV-025"],
    "status": "NeedsReview",
    "confidence": 40,
    "rawText": "Payment covers invoices from subsidiary accounts. See attached breakdown."
  },
  {
    "id": "REM-011",
    "source": "Portal",
    "receivedAt": "2024-12-09T08:55:00Z",
    "payerName": "SAP SE",
    "customerId": "C-SAP",
    "paymentId": "PAY-021",
    "documentType": "XML",
    "fileName": "SAP_PAIN_001_120924.xml",
    "extractedAmount": 112000.00,
    "invoiceReferences": ["INV-028", "INV-029"],
    "status": "Processed",
    "confidence": 93,
    "rawText": null
  },
  {
    "id": "REM-012",
    "source": "Email",
    "receivedAt": "2024-12-10T06:55:00Z",
    "payerName": "Datadog Inc",
    "customerId": "C-DDOG",
    "paymentId": "PAY-022",
    "documentType": "PDF",
    "fileName": "Datadog_Remit_121024.pdf",
    "extractedAmount": 28400.00,
    "invoiceReferences": ["INV-030"],
    "status": "Processed",
    "confidence": 89,
    "rawText": "EFT payment for INV-030. Amount: $28,400.00"
  },
  {
    "id": "REM-013",
    "source": "Portal",
    "receivedAt": "2024-12-11T05:55:00Z",
    "payerName": "Netflix Inc",
    "customerId": "C-NFLX",
    "paymentId": "PAY-025",
    "documentType": "CSV",
    "fileName": "Netflix_Payment_121124.csv",
    "extractedAmount": 189500.00,
    "invoiceReferences": ["INV-033", "INV-034", "INV-035"],
    "status": "Processed",
    "confidence": 99,
    "rawText": null
  },
  {
    "id": "REM-014",
    "source": "Email",
    "receivedAt": "2024-12-12T07:25:00Z",
    "payerName": "Uber Technologies",
    "customerId": "C-UBER",
    "paymentId": "PAY-026",
    "documentType": "PDF",
    "fileName": "Uber_Remit_121224.pdf",
    "extractedAmount": 42300.00,
    "invoiceReferences": ["INV-036"],
    "status": "Processed",
    "confidence": 95,
    "rawText": "Payment for INV-036. Thank you for your services."
  },
  {
    "id": "REM-015",
    "source": "Lockbox",
    "receivedAt": "2024-12-13T13:55:00Z",
    "payerName": "Square Inc",
    "customerId": "C-SQ",
    "paymentId": "PAY-028",
    "documentType": "CheckStub",
    "fileName": "Lockbox_Batch_121324_028.tif",
    "extractedAmount": 8250.00,
    "invoiceReferences": ["INV-038"],
    "status": "Pending",
    "confidence": null,
    "rawText": "Check #11204 - Block Inc payment"
  }
]
